goddaniel/__init__.py
goddaniel/goddaniel.py
goddaniel/plotting.py
goddaniel-0.1.0.dist-info/LICENSE
goddaniel-0.1.0.dist-info/METADATA
goddaniel-0.1.0.dist-info/WHEEL
goddaniel-0.1.0.dist-info/RECORD
